pve_clone/__init__.py
pve_clone/__main__.py
pve_clone/py.typed
pve_clone-1.0.7.dist-info/LICENSE
pve_clone-1.0.7.dist-info/METADATA
pve_clone-1.0.7.dist-info/WHEEL
pve_clone-1.0.7.dist-info/entry_points.txt
pve_clone-1.0.7.dist-info/top_level.txt
pve_clone-1.0.7.dist-info/RECORD
