Metadata-Version: 2.1
Name: pve-clone
Version: 1.0.7
Author-email: Pradish Bijukchhe <pradish@sandbox.com.np>
License: Copyright (c) 2018 The Python Packaging Authority
Project-URL: Homepage, https://github.com/sandbox-pokhara/pve-clone
Project-URL: Issues, https://github.com/sandbox-pokhara/pve-clone/issues
Classifier: Programming Language :: Python :: 3
Requires-Python: >=3
License-File: LICENSE
Requires-Dist: ch9329
